invoice_pdfgen/__init__.py
invoice_pdfgen/pdf_invoice_generator.py
invoice_pdfgen-1.2.3.dist-info/LICENSE
invoice_pdfgen-1.2.3.dist-info/METADATA
invoice_pdfgen-1.2.3.dist-info/WHEEL
invoice_pdfgen-1.2.3.dist-info/top_level.txt
invoice_pdfgen-1.2.3.dist-info/RECORD
